{
  "id": "ErimSEVER/11",
  "name": "Hex 11",
  "author": "Erim SEVER",
  "source": "www.erimsever.com/sokoban/Erim_Levels/E_Hexoban.zip",
  "terrain": [
    [-2, 0], [-1, -1], [0, -2], [-2, 1], [-1, 0], [0, -1], [1, -2], [-2, 2], [-1, 1], [0, 0], [1, -1], [2, -2], [-1, 2], [0, 1], [1, 0], [2, -1], [0, 2], [1, 1], [2, 0]
  ],
  "init": {
    "goals": [
      [0, -2], [0, -1], [-2, 2], [-1, 1], [1, 0], [2, 0]
    ],
    "crates": [
      [-1, 0], [0, -1], [-1, 1], [1, -1], [0, 1], [1, 0]
    ]
  }
}